ctplite
