Metadata-Version: 2.1
Name: ctplite
Version: 0.1.7
Summary: Python SDK for pq-futures CTP trading system
Home-page: https://www.ctplite.com
Author: pq-futures
Author-email: ctplite@163.com
License: MIT
Keywords: ctp,trading,futures,grpc,rest,sdk
Classifier: Development Status :: 3 - Alpha
Classifier: Intended Audience :: Developers
Classifier: License :: OSI Approved :: MIT License
Classifier: Programming Language :: Python :: 3
Classifier: Programming Language :: Python :: 3.8
Classifier: Programming Language :: Python :: 3.9
Classifier: Programming Language :: Python :: 3.10
Classifier: Programming Language :: Python :: 3.11
Classifier: Topic :: Software Development :: Libraries :: Python Modules
Classifier: Topic :: Office/Business :: Financial :: Investment
Requires-Python: >=3.8
License-File: LICENSE
Requires-Dist: grpcio>=1.70.0
Requires-Dist: grpcio-tools>=1.70.0
Requires-Dist: protobuf>=5.29.5
Requires-Dist: requests>=2.31.0
Requires-Dist: python-dotenv>=1.0.0
Provides-Extra: dev
Requires-Dist: pytest>=7.0.0; extra == "dev"
Requires-Dist: pytest-cov>=4.0.0; extra == "dev"
Requires-Dist: black>=23.0.0; extra == "dev"
Requires-Dist: flake8>=6.0.0; extra == "dev"
